dr.who-9.1.1-py3.8-nspkg.pth
dr/who/__init__.py
dr/who/_version.py
dr/who/zipper.py
dr/who/tests/__init__.py
dr.who-9.1.1.dist-info/METADATA
dr.who-9.1.1.dist-info/WHEEL
dr.who-9.1.1.dist-info/entry_points.txt
dr.who-9.1.1.dist-info/namespace_packages.txt
dr.who-9.1.1.dist-info/top_level.txt
dr.who-9.1.1.dist-info/zip-safe
dr.who-9.1.1.dist-info/RECORD
