Metadata-Version: 2.1
Name: dr.who
Version: 9.1.1
Summary: Package Reservation testing whatever
Home-page: http://pypi.python.org/pypi/dr.who
Author: Sean Kelly
Author-email: kelly@seankelly.biz
License: ALv2
Keywords: placeholder
Platform: UNKNOWN
Classifier: Development Status :: 1 - Planning
Classifier: Environment :: Other Environment
Classifier: License :: OSI Approved :: Apache Software License
Classifier: Operating System :: OS Independent
Classifier: Programming Language :: Python
Requires-Dist: setuptools
Provides-Extra: test
